pykblib/__init__.py
pykblib/api.py
pykblib/classes.py
pykblib/const.py
pykblib/exceptions.py
pykblib/functions.py
pykblib/keybase.py
pykblib/pykblib.old.py
pykblib/pykblib.py
pykblib/pykeybase.old.py
pykblib/pykeybase.py
pykblib/team.py
PyKBLib-2.0.0.dist-info/LICENSE
PyKBLib-2.0.0.dist-info/METADATA
PyKBLib-2.0.0.dist-info/WHEEL
PyKBLib-2.0.0.dist-info/top_level.txt
PyKBLib-2.0.0.dist-info/RECORD
