Metadata-Version: 2.1
Name: PyKBLib
Version: 2.0.0
Summary: A Python library for interacting with the Keybase CLI tools.
Home-page: https://github.com/cmsteffen-code/PyKBLib
Author: CMSteffen
Author-email: cmsteffen@protonmail.com
License: MIT
Project-URL: Source Code, https://github.com/cmsteffen-code/PyKBLib
Project-URL: Documentation, https://pykblib.readthedocs.io/en/latest/
Keywords: pykblib keybase library
Platform: UNKNOWN
Classifier: Development Status :: 2 - Pre-Alpha
Classifier: Intended Audience :: Developers
Classifier: License :: OSI Approved :: MIT License
Classifier: Programming Language :: Python :: 3
Classifier: Programming Language :: Python :: 3.5
Classifier: Programming Language :: Python :: 3.6
Classifier: Programming Language :: Python :: 3.7
Classifier: Topic :: Communications
Classifier: Topic :: Communications :: Chat
Classifier: Topic :: Security
Classifier: Topic :: Security :: Cryptography
Classifier: Topic :: Software Development :: Libraries
Requires-Dist: steffentools (>=0.1.0)
